pypi_mr/__init__.py
pypi_mr/cleanup.py
pypi_mr/exists.py
pypi_mr/util.py
pypi_mr-0.0.4.dist-info/METADATA
pypi_mr-0.0.4.dist-info/WHEEL
pypi_mr-0.0.4.dist-info/top_level.txt
pypi_mr-0.0.4.dist-info/RECORD
