Metadata-Version: 2.1
Name: pypi-mr
Version: 0.0.4
Summary: Check if package exists on pypi registry using simple API. Clean packages that belongs to closed/merged GitLab MRs
Author-email: Alexander Rodionov <tandav@tandav.me>
Project-URL: source, https://github.com/tandav/pypi-mr
Project-URL: docs, https://tandav.github.io/pypi-mr/
Project-URL: issues, https://github.com/tandav/pypi-mr/issues
Project-URL: release notes, https://github.com/tandav/pypi-mr/releases
Requires-Python: >=3.9
Requires-Dist: requests
Requires-Dist: packaging
Provides-Extra: dev
Requires-Dist: bumpver ; extra == 'dev'
Requires-Dist: pre-commit ; extra == 'dev'
Requires-Dist: pytest ; extra == 'dev'
